aligntools/__init__.py
aligntools/cigar.py
aligntools/cigar_actions.py
aligntools/cigar_hit.py
aligntools/comparable.py
aligntools/coordinate_mapping.py
aligntools/exceptions.py
aligntools/int_dict.py
aligntools/py.typed
aligntools-1.2.2.dist-info/METADATA
aligntools-1.2.2.dist-info/WHEEL
aligntools-1.2.2.dist-info/licenses/COPYING
aligntools-1.2.2.dist-info/RECORD
