Metadata-Version: 2.4
Name: aligntools
Version: 1.2.2
Summary: A Python library for manipulation of CIGAR, MSA, and other alignment formats.
Project-URL: Homepage, https://github.com/cfe-lab/aligntools
Author-email: British Columbia Centre for Excellence in HIV/AIDS <vmysak@bccfe.ca>
License-Expression: AGPL-3.0
License-File: COPYING
Classifier: Development Status :: 5 - Production/Stable
Classifier: Intended Audience :: Developers
Classifier: Intended Audience :: Science/Research
Classifier: License :: OSI Approved :: GNU Affero General Public License v3
Classifier: Natural Language :: English
Classifier: Operating System :: OS Independent
Classifier: Programming Language :: Python
Classifier: Programming Language :: Python :: 3
Classifier: Programming Language :: Python :: 3.8
Classifier: Programming Language :: Python :: 3.9
Classifier: Programming Language :: Python :: 3.10
Classifier: Programming Language :: Python :: 3.11
Classifier: Programming Language :: Python :: 3.12
Classifier: Programming Language :: Python :: 3.13
Classifier: Programming Language :: Python :: Implementation :: CPython
Classifier: Topic :: Scientific/Engineering :: Bio-Informatics
Classifier: Topic :: Software Development :: Libraries
Classifier: Typing :: Typed
Provides-Extra: dev
Requires-Dist: bandit; extra == 'dev'
Requires-Dist: mypy==1.9.0; extra == 'dev'
Requires-Dist: ruff; extra == 'dev'
Provides-Extra: test
Requires-Dist: pytest-cov; extra == 'test'
Requires-Dist: pytest>=6.0; extra == 'test'
